mseep_steampipe_mcp_server-0.2.3.dist-info/licenses/LICENSE
tests/__init__.py
tests/test_db_service.py
mseep_steampipe_mcp_server-0.2.3.dist-info/METADATA
mseep_steampipe_mcp_server-0.2.3.dist-info/WHEEL
mseep_steampipe_mcp_server-0.2.3.dist-info/entry_points.txt
mseep_steampipe_mcp_server-0.2.3.dist-info/top_level.txt
mseep_steampipe_mcp_server-0.2.3.dist-info/RECORD
