Metadata-Version: 2.4
Name: mseep-steampipe-mcp-server
Version: 0.2.3
Summary: A Python MCP server interacting with PostgreSQL, intended for use with Steampipe.
Home-page: 
Author: mseep
Author-email: mseep <support@skydeck.ai>
Maintainer-email: mseep <support@skydeck.ai>
License: MIT
Keywords: mcp,llm,postgres,postgresql,steampipe
Classifier: Development Status :: 4 - Beta
Classifier: Intended Audience :: Developers
Classifier: License :: OSI Approved :: MIT License
Classifier: Programming Language :: Python :: 3
Classifier: Programming Language :: Python :: 3.10
Classifier: Programming Language :: Python :: 3.11
Classifier: Programming Language :: Python :: 3.12
Requires-Python: >=3.6
License-File: LICENSE
Requires-Dist: mcp[cli]>=1.6.0
Requires-Dist: psycopg[binary,pool]>=3.1.0
Requires-Dist: pydantic>=2.0.0
Requires-Dist: click>=8.1.8
Provides-Extra: dev
Requires-Dist: ruff>=0.8.5; extra == "dev"
Requires-Dist: pyright>=1.1.391; extra == "dev"
Requires-Dist: pytest>=7.0.0; extra == "dev"
Requires-Dist: pytest-asyncio>=0.21.0; extra == "dev"
Requires-Dist: build>=1.0.0; extra == "dev"
Dynamic: author
Dynamic: license-file
Dynamic: requires-python
